envariable/__init__.py
envariable/unix.py
envariable/windows.py
envariable-1.3.dist-info/LICENSE
envariable-1.3.dist-info/METADATA
envariable-1.3.dist-info/WHEEL
envariable-1.3.dist-info/top_level.txt
envariable-1.3.dist-info/RECORD
