Metadata-Version: 2.1
Name: envariable
Version: 1.3
Summary: Change System Environment Variable permanently
Home-page: https://github.com/blueboy-tm/python-envariable/
Author: Arshia Ihammi
Author-email: arshiaihammi@gmail.com
License: MIT
Download-URL: https://github.com/blueboy-tm/python-envariable/raw/main/dist/envariable-1.3.tar.gz
Keywords: env,variable,environment,os,system,Environment Variable,environ
Platform: UNKNOWN
Classifier: Development Status :: 5 - Production/Stable
Classifier: Intended Audience :: Developers
Classifier: Topic :: System
Classifier: License :: OSI Approved :: MIT License
Classifier: Programming Language :: Python :: 3
Classifier: Programming Language :: Python :: 3.3
Classifier: Programming Language :: Python :: 3.4
Classifier: Programming Language :: Python :: 3.5
Classifier: Programming Language :: Python :: 3.6
Classifier: Programming Language :: Python :: 3.7
Classifier: Programming Language :: Python :: 3.8
Classifier: Programming Language :: Python :: 3.9
Classifier: Programming Language :: Python :: 3 :: Only
Requires-Python: ~=3.3
